pcats_api_client/__init__.py
pcats_api_client/pcats_api.py
pcats_api_client/pcats_api_staticgp2.py
pcats_api_client-1.1.1.dist-info/METADATA
pcats_api_client-1.1.1.dist-info/WHEEL
pcats_api_client-1.1.1.dist-info/top_level.txt
pcats_api_client-1.1.1.dist-info/RECORD
