Metadata-Version: 2.1
Name: pcats-api-client
Version: 1.1.1
Summary: PCATS REST API Client
Home-page: https://github.com/pcats-api/pcats_api_client_py
Author: Michal Kouril
Author-email: michal.kouril@cchmc.org
License: MIT
Requires-Dist: requests
